paracrine/__init__.py
paracrine/deps.py
paracrine/runner.py
paracrine/commands/__init__.py
paracrine/commands/login.py
paracrine/commands/reboot.py
paracrine/commands/setup.py
paracrine/commands/sftp.py
paracrine/helpers/__init__.py
paracrine/helpers/config.py
paracrine/helpers/cron.py
paracrine/helpers/debian.py
paracrine/helpers/fs.py
paracrine/helpers/network.py
paracrine/helpers/python.py
paracrine/helpers/systemd.py
paracrine/helpers/users.py
paracrine/runners/__init__.py
paracrine/runners/aws.py
paracrine/runners/certs.py
paracrine/runners/core.py
paracrine/services/__init__.py
paracrine/services/ntp.py
paracrine/services/pleroma.py
paracrine/services/postgresql.py
paracrine/services/cockroachdb/__init__.py
paracrine/services/cockroachdb/certs.py
paracrine/services/cockroachdb/common.py
paracrine/services/cockroachdb/init.py
paracrine/services/cockroachdb/node.py
paracrine/services/redis/__init__.py
paracrine/services/redis/check_master.py
paracrine/services/redis/common.py
paracrine/services/redis/init.py
paracrine/services/redis/node.py
paracrine/services/redis/wipe_old_master.py
paracrine/services/wireguard/__init__.py
paracrine/services/wireguard/bootstrap.py
paracrine/services/wireguard/common.py
paracrine/services/wireguard/core.py
paracrine/templates/certbot_requirements.txt
paracrine/templates/cockroach.service.j2
paracrine/templates/config.exs.j2
paracrine/templates/cron.j2
paracrine/templates/pleroma.nginx.j2
paracrine/templates/redis-sentinel.conf.j2
paracrine/templates/redis.conf.j2
paracrine/templates/robots.txt
paracrine/templates/setup_db.psql.j2
paracrine/templates/wg.conf.j2
paracrine-0.2.1.dist-info/LICENSE
paracrine-0.2.1.dist-info/METADATA
paracrine-0.2.1.dist-info/WHEEL
paracrine-0.2.1.dist-info/top_level.txt
paracrine-0.2.1.dist-info/RECORD
