Metadata-Version: 2.1
Name: paracrine
Version: 0.2.1
Summary: A system deployment tool
Author-email: Tom Parker-Shemilt <palfrey@tevp.net>
Project-URL: Homepage, https://github.com/palfrey/paracrine
Project-URL: Bug Tracker, https://github.com/palfrey/paracrine/issues
Classifier: Programming Language :: Python :: 3
Classifier: License :: OSI Approved :: GNU Affero General Public License v3
Classifier: Operating System :: OS Independent
Requires-Python: >=3.9
License-File: LICENSE
Requires-Dist: mitogen
Requires-Dist: jinja2
Requires-Dist: pyyaml
Requires-Dist: python-debian
Requires-Dist: mergedeep
Requires-Dist: retry
Requires-Dist: requests
Requires-Dist: typing-extensions
Requires-Dist: frozendict
